MANIFEST.in
README.txt
setup.py
docs/HISTORY.txt
src/zeam/__init__.py
src/zeam.component.egg-info/PKG-INFO
src/zeam.component.egg-info/SOURCES.txt
src/zeam.component.egg-info/dependency_links.txt
src/zeam.component.egg-info/namespace_packages.txt
src/zeam.component.egg-info/not-zip-safe
src/zeam.component.egg-info/requires.txt
src/zeam.component.egg-info/top_level.txt
src/zeam/component/__init__.py
src/zeam/component/components.py
src/zeam/component/configure.zcml
src/zeam/component/martiansupport.py
src/zeam/component/site.py