Metadata-Version: 1.0
Name: zeam.component
Version: 1.0
Summary: Component infrastructure, based on zope.interface
Home-page: http://pypi.python.org/pypi/zeam.component
Author: Sylvain Viollon
Author-email: thefunny@gmail.com
License: BSD
Keywords: component interface
Platform: UNKNOWN
Classifier: Programming Language :: Python
Classifier: Topic :: Software Development :: Libraries :: Python Modules
